matplotlib_inline/__init__.py
matplotlib_inline/backend_inline.py
matplotlib_inline/config.py
matplotlib_inline-0.1.5.dist-info/LICENSE
matplotlib_inline-0.1.5.dist-info/METADATA
matplotlib_inline-0.1.5.dist-info/WHEEL
matplotlib_inline-0.1.5.dist-info/top_level.txt
matplotlib_inline-0.1.5.dist-info/RECORD
