Metadata-Version: 2.1
Name: matplotlib-inline
Version: 0.1.5
Summary: Inline Matplotlib backend for Jupyter
Home-page: https://github.com/ipython/matplotlib-inline
Author: IPython Development Team
Author-email: ipython-dev@scipy.org
License: BSD 3-Clause
Keywords: python,ipython,matplotlib,jupyter
Requires-Python: >=3.5
License-File: LICENSE
